base/__init__.py
base/construct.py
base/interview_transcript.py
base/pipeline.py
base/transcript.py
base/video_transcript.py
docs/__init__.py
eazynlp/__init__.py
eazynlp/base/__init__.py
eazynlp/base/construct.py
eazynlp/base/interview_transcript.py
eazynlp/base/pipeline.py
eazynlp/base/transcript.py
eazynlp/base/video_transcript.py
eazynlp/model_evaluator/__init__.py
eazynlp/text_cleaner/__init__.py
eazynlp/text_cleaner/cleaner.py
eazynlp/text_cleaner/punctuation_cleaner.py
eazynlp/text_cleaner/stopword_cleaner.py
eazynlp/text_cleaner/wordcase_cleaner.py
eazynlp/text_loader/__init__.py
eazynlp/text_loader/loader.py
eazynlp/text_miner/__init__.py
eazynlp/text_miner/analysis.py
eazynlp/text_miner/classifier_analysis.py
eazynlp/text_miner/cluster_analysis.py
eazynlp/text_miner/decomposition_analysis.py
eazynlp/text_miner/similarity_analysis.py
eazynlp/text_miner/topicmodel_analysis.py
eazynlp/text_miner/wordcount_analysis.py
eazynlp/text_miner/wordcount_analysis_oldversion.py
eazynlp/text_transformer/__init__.py
eazynlp/validator/__init__.py
eazynlp/validator/construct_validator.py
eazynlp/visualizer/__init__.py
eazynlp/visualizer/visualizer.py
model_evaluator/__init__.py
tests/__init__.py
tests/test_utils.py
text_cleaner/__init__.py
text_cleaner/cleaner.py
text_cleaner/punctuation_cleaner.py
text_cleaner/stopword_cleaner.py
text_cleaner/wordcase_cleaner.py
text_loader/__init__.py
text_loader/loader.py
text_miner/__init__.py
text_miner/analysis.py
text_miner/classifier_analysis.py
text_miner/cluster_analysis.py
text_miner/decomposition_analysis.py
text_miner/similarity_analysis.py
text_miner/topicmodel_analysis.py
text_miner/wordcount_analysis.py
text_miner/wordcount_analysis_oldversion.py
text_transformer/__init__.py
validator/__init__.py
validator/construct_validator.py
visualizer/__init__.py
visualizer/visualizer.py
eazynlp-0.0.7.dist-info/LICENSE
eazynlp-0.0.7.dist-info/METADATA
eazynlp-0.0.7.dist-info/WHEEL
eazynlp-0.0.7.dist-info/top_level.txt
eazynlp-0.0.7.dist-info/RECORD
