Metadata-Version: 2.1
Name: eazynlp
Version: 0.0.7
Summary: NLP made easy for researchers
Home-page: https://github.com/tumeri/eazynlp
Author: Info CodeBrew
Author-email: info.codebrew@gmail.com
License: UNKNOWN
Platform: UNKNOWN
Classifier: Programming Language :: Python :: 3
Classifier: License :: OSI Approved :: GNU General Public License v3 or later (GPLv3+)
Classifier: Operating System :: OS Independent
Requires-Python: >=3.6
Requires-Dist: matplotlib
Requires-Dist: nltk
Requires-Dist: pandas
Requires-Dist: wordcloud
